MANIFEST.in
README.rst
setup.cfg
setup.py
baseball_id/__init__.py
baseball_id/factory.py
baseball_id/lookup.py
baseball_id/sample.master.csv
baseball_id.egg-info/PKG-INFO
baseball_id.egg-info/SOURCES.txt
baseball_id.egg-info/dependency_links.txt
baseball_id.egg-info/requires.txt
baseball_id.egg-info/top_level.txt
baseball_id.egg-info/zip-safe