Metadata-Version: 1.2
Name: baseball-id
Version: 0.0.5
Summary: Lookup baseball players by their ID at various data sources like MLB, Yahoo!, CBS, ESPN, and FanGraphs.
Home-page: http://github.com/spilchen/baseball_id
Author: Matt Spilchen
Author-email: matt.spilchen@gmail.com
License: MIT
Platform: UNKNOWN
Classifier: Development Status :: 3 - Alpha
Classifier: Intended Audience :: Developers
Classifier: License :: OSI Approved :: MIT License
Classifier: Programming Language :: Python :: 3.7
Requires-Python: >=3
